zope/testbrowser/__init__.py
zope/testbrowser/browser.py
zope/testbrowser/cookies.py
zope/testbrowser/fixed-bugs.txt
zope/testbrowser/interfaces.py
zope/testbrowser/over_the_wire.txt
zope/testbrowser/testing.py
zope/testbrowser/utils.py
zope/testbrowser/wsgi.py
zope/testbrowser/ftests/__init__.py
zope/testbrowser/ftests/controls.html
zope/testbrowser/ftests/cookies.html
zope/testbrowser/ftests/forms.html
zope/testbrowser/ftests/fragment.html
zope/testbrowser/ftests/navigate.html
zope/testbrowser/ftests/notitle.html
zope/testbrowser/ftests/oneform.html
zope/testbrowser/ftests/radio.html
zope/testbrowser/ftests/simple.html
zope/testbrowser/ftests/status_lead.html
zope/testbrowser/ftests/textarea.html
zope/testbrowser/ftests/wsgitestapp.py
zope/testbrowser/ftests/zope3logo.gif
zope/testbrowser/tests/__init__.py
zope/testbrowser/tests/helper.py
zope/testbrowser/tests/test_bbb.py
zope/testbrowser/tests/test_browser.py
zope/testbrowser/tests/test_cookies.py
zope/testbrowser/tests/test_doctests.py
zope/testbrowser/tests/test_wsgi.py
zope_testbrowser-8.0.dist-info/licenses/LICENSE.rst
zope_testbrowser-8.0.dist-info/METADATA
zope_testbrowser-8.0.dist-info/WHEEL
zope_testbrowser-8.0.dist-info/top_level.txt
zope_testbrowser-8.0.dist-info/RECORD
