Metadata-Version: 2.4
Name: zope.testbrowser
Version: 8.0
Summary: Programmable browser for functional black-box tests
Home-page: https://github.com/zopefoundation/zope.testbrowser
Author: Zope Foundation and Contributors
Author-email: zope-dev@zope.dev
License: ZPL-2.1
Project-URL: Documentation, https://zopetestbrowser.readthedocs.io/
Keywords: headless browser functional tests WSGI HTTP HTML form
Classifier: Environment :: Web Environment
Classifier: Intended Audience :: Developers
Classifier: License :: OSI Approved :: Zope Public License
Classifier: Programming Language :: Python :: 3
Classifier: Programming Language :: Python :: 3.9
Classifier: Programming Language :: Python :: 3.10
Classifier: Programming Language :: Python :: 3.11
Classifier: Programming Language :: Python :: 3.12
Classifier: Programming Language :: Python :: 3.13
Classifier: Programming Language :: Python :: Implementation :: CPython
Classifier: Programming Language :: Python :: Implementation :: PyPy
Classifier: Topic :: Software Development :: Testing
Classifier: Topic :: Internet :: WWW/HTTP
Requires-Python: >=3.9
License-File: LICENSE.rst
Requires-Dist: setuptools
Requires-Dist: zope.interface
Requires-Dist: zope.schema
Requires-Dist: zope.cachedescriptors
Requires-Dist: pytz
Requires-Dist: WebTest>=2.0.30
Requires-Dist: BeautifulSoup4
Requires-Dist: SoupSieve>=1.9.0
Requires-Dist: WSGIProxy2
Requires-Dist: legacy-cgi; python_version > "3.12"
Provides-Extra: docs
Requires-Dist: Sphinx; extra == "docs"
Requires-Dist: sphinx_rtd_theme; extra == "docs"
Requires-Dist: repoze.sphinx.autointerface; extra == "docs"
Requires-Dist: zope.app.wsgi; extra == "docs"
Provides-Extra: test
Requires-Dist: zope.testing; extra == "test"
Requires-Dist: mock; extra == "test"
Requires-Dist: zope.testrunner>=6.4; extra == "test"
Provides-Extra: test-bbb
Requires-Dist: zope.testbrowser[test]; extra == "test-bbb"
Provides-Extra: wsgi
Dynamic: author
Dynamic: author-email
Dynamic: classifier
Dynamic: description
Dynamic: home-page
Dynamic: keywords
Dynamic: license
Dynamic: license-file
Dynamic: project-url
Dynamic: provides-extra
Dynamic: requires-dist
Dynamic: requires-python
Dynamic: summary
